imquality/__init__.py
imquality/brisque.py
imquality/statistics.py
imquality/utils.py
imquality/datasets/__init__.py
imquality/datasets/live_iqa.py
imquality/datasets/tid2013.py
imquality/datasets/url_checksums/live_iqa.txt
imquality/datasets/url_checksums/tid2013.txt
imquality/models/__init__.py
imquality/models/brisque_svm.txt
imquality/models/normalize.pickle
image_quality-1.2.6.dist-info/LICENSE
image_quality-1.2.6.dist-info/METADATA
image_quality-1.2.6.dist-info/WHEEL
image_quality-1.2.6.dist-info/top_level.txt
image_quality-1.2.6.dist-info/RECORD
