Metadata-Version: 2.1
Name: image-quality
Version: 1.2.6
Summary: Image quality is an open source software library for Automatic Image Quality Assessment (IQA).
Home-page: https://github.com/ocampor/image-quality
Author: Ricardo Ocampo
Author-email: me@ocampor.ai
License: Apache 2.0
Project-URL: Bug Tracker, https://github.com/ocampor/image-quality/issues
Project-URL: Source Code, https://github.com/ocampor/image-quality
Keywords: image,quality,reference,reference-less
Platform: UNKNOWN
Classifier: Intended Audience :: Developers
Classifier: Topic :: Scientific/Engineering :: Artificial Intelligence
Classifier: Topic :: Scientific/Engineering :: Image Recognition
Classifier: License :: OSI Approved :: Apache Software License
Classifier: Programming Language :: Python :: 3.7
Classifier: Programming Language :: Python :: 3.8
Classifier: Operating System :: Microsoft :: Windows :: Windows 10
Classifier: Operating System :: MacOS
Classifier: Operating System :: POSIX :: Linux
Requires-Python: >=3.6
Requires-Dist: Pillow (>=5.2.0)
Requires-Dist: numpy (>=1.16.4)
Requires-Dist: scipy (>=1.3.0)
Requires-Dist: scikit-image (>=0.15.0)
Requires-Dist: libsvm (>=3.23.0)
Provides-Extra: dataset
Requires-Dist: tensorflow (>=2.0.0) ; extra == 'dataset'
Requires-Dist: tensorflow-datasets (>=1.2.0) ; extra == 'dataset'
Provides-Extra: dev
Requires-Dist: pytest (>=4.4.0) ; extra == 'dev'
Requires-Dist: pytest-xdist ; extra == 'dev'
Requires-Dist: black (>=20.8b1) ; extra == 'dev'
